.travis.yml
LICENSE
MANIFEST.in
Makefile
dev-requirements.txt
setup.cfg
setup.py
tox.ini
jobs_detector/__init__.py
jobs_detector/exceptions.py
jobs_detector/main.py
jobs_detector/settings.py
rmotr_b14_cpyp_g1_jobs_detector.egg-info/PKG-INFO
rmotr_b14_cpyp_g1_jobs_detector.egg-info/SOURCES.txt
rmotr_b14_cpyp_g1_jobs_detector.egg-info/dependency_links.txt
rmotr_b14_cpyp_g1_jobs_detector.egg-info/not-zip-safe
rmotr_b14_cpyp_g1_jobs_detector.egg-info/top_level.txt
tests/__init__.py
tests/test_main.py